clients/__init__.py
clients/arcgis.py
clients/exceptions.py
clients/query/__init__.py
clients/query/actions.py
clients/query/arcgis.py
clients/query/fields.py
clients/query/serializers.py
clients/resources.py
clients/sciencebase.py
clients/tests/__init__.py
clients/tests/arcgis_tests.py
clients/tests/conversion_tests.py
clients/tests/data/arcgis/config-error.json
clients/tests/data/arcgis/empty-error.json
clients/tests/data/arcgis/error.html
clients/tests/data/arcgis/feature-layer-ids.json
clients/tests/data/arcgis/feature-layer-version-error.json
clients/tests/data/arcgis/feature-layer.json
clients/tests/data/arcgis/feature-version-error.json
clients/tests/data/arcgis/feature.json
clients/tests/data/arcgis/generic-error.json
clients/tests/data/arcgis/geometry.json
clients/tests/data/arcgis/image-version-error.json
clients/tests/data/arcgis/image.json
clients/tests/data/arcgis/map-layer-version-error.json
clients/tests/data/arcgis/map-layer.json
clients/tests/data/arcgis/map-layers.json
clients/tests/data/arcgis/map-legend.json
clients/tests/data/arcgis/map-version-error.json
clients/tests/data/arcgis/map.json
clients/tests/data/arcgis/no-feature-layer.json
clients/tests/data/arcgis/no-map-layers-layers.json
clients/tests/data/arcgis/no-map-layers.json
clients/tests/data/arcgis/not-found.json
clients/tests/data/arcgis/token-required.json
clients/tests/data/resources/test-client-bulk-keys.json
clients/tests/data/resources/test-client-bulk.json
clients/tests/data/resources/test-client.json
clients/tests/data/resources/test-invalid-json.html
clients/tests/data/resources/test-invalid-max.json
clients/tests/data/resources/test-invalid-min.json
clients/tests/data/sciencebase/arcgis-item.json
clients/tests/data/sciencebase/arcgis-service-layer.json
clients/tests/data/sciencebase/arcgis-service-layers.json
clients/tests/data/sciencebase/arcgis-service-legend.json
clients/tests/data/sciencebase/arcgis-service.json
clients/tests/data/sciencebase/deprecated.json
mapservice_clientlib-2.3.0.dist-info/LICENSE
mapservice_clientlib-2.3.0.dist-info/METADATA
mapservice_clientlib-2.3.0.dist-info/WHEEL
mapservice_clientlib-2.3.0.dist-info/RECORD
