Metadata-Version: 2.1
Name: mapservice-clientlib
Version: 2.3.0
Summary: Library to query mapservices including ArcGIS, THREDDS, WMS and ScienceBase
Home-page: https://github.com/consbio/mapservice-clientlib/
License: BSD
Keywords: arcgis,thredds,ncwms,wms,sciencebase,geospatial,gis,mapservice,map service,clients,mapservice_clientlib
Author: dharvey-consbio
Author-email: dani.harvey@consbio.org
Requires-Python: >=3.8,<4.0
Classifier: License :: Other/Proprietary License
Classifier: Programming Language :: Python :: 3
Classifier: Programming Language :: Python :: 3.8
Classifier: Programming Language :: Python :: 3.9
Classifier: Programming Language :: Python :: 3.10
Classifier: Programming Language :: Python :: 3.11
Requires-Dist: Pillow (>=9.5,<10.0)
Requires-Dist: gis-metadata-parser (>=2.0,<3.0)
Requires-Dist: parserutils (>=2.0.1,<3.0.0)
Requires-Dist: pyproj (>=3.2.1,<4.0.0)
Requires-Dist: python-ags (>=0.3.2,<0.4.0)
Requires-Dist: restle (>=0.5.1,<0.6.0)
Requires-Dist: sciencebasepy (>=2.0.4,<3.0.0)
Project-URL: Repository, https://github.com/consbio/mapservice-clientlib/
